pysst/VERSION
pysst/__init__.py
pysst/pymrd.py
pysst/pymrd_sum_folder.py
pysst/rules/standard_names.yaml
pysst-0.1.1.dist-info/LICENSE
pysst-0.1.1.dist-info/METADATA
pysst-0.1.1.dist-info/WHEEL
pysst-0.1.1.dist-info/top_level.txt
pysst-0.1.1.dist-info/RECORD
